sqlite_magic/__init__.py
sqlite_magic/sqlite_magic.py
sqlite_magic-0.2.0.dist-info/WHEEL
sqlite_magic-0.2.0.dist-info/METADATA
sqlite_magic-0.2.0.dist-info/RECORD
