Metadata-Version: 2.1
Name: sqlite-magic
Version: 0.2.0
Summary: 
Author: Todd Iverson
Author-email: Tiverson@winona.edu
Requires-Python: >=3.8
Classifier: Programming Language :: Python :: 3
Classifier: Programming Language :: Python :: 3.8
Classifier: Programming Language :: Python :: 3.9
Classifier: Programming Language :: Python :: 3.10
Classifier: Programming Language :: Python :: 3.11
Requires-Dist: ipython (>=6.0.0)
Requires-Dist: pandas (>=1.0.0)
